{
  "english": {
    "front_face": {
      "title": "FRONT FACE",
      "mean_time": "MEAN TIME",
      "mean_time_subtitle": "(Clock Time)",
      "apparent_time": "APPARENT TIME",
      "apparent_time_subtitle": "(Sundial Time)",
      "sundial_ahead": "Sundial AHEAD",
      "sundial_behind": "Sundial BEHIND",
      "local_time": "Local Time"
    },
    "back_upper_face": {
      "title": "Metonic Cycle",
      "year_month": "Year {year}/19 — Month {month}/235",
      "cycle_ends": "Cycle ends in {years}y {days}d (19.0 solar years)",
      "progress": "Progress: {percent}%",
      "callippic": "Callippic",
      "years_76": "76 years"
    },
    "back_lower_face": {
      "title": "Saros Cycle",
      "saros_month": "Saros Cycle {cycle} — Month {month}/223",
      "cycle_ends": "Cycle ends in {years}y {days}d (≈ 6586.3 days total)",
      "next_eclipse_solar": "Next Eclipse: Solar ☉ in {days} days",
      "next_eclipse_lunar": "Next Eclipse: Lunar ☽ in {days} days",
      "progress": "Progress: {percent}%",
      "exeligmos": "Exeligmos",
      "years_54": "54 years"
    },
    "zodiac": {
      "aries": "ARIES",
      "taurus": "TAURUS",
      "gemini": "GEMINI",
      "cancer": "CANCER",
      "leo": "LEO",
      "virgo": "VIRGO",
      "libra": "LIBRA",
      "scorpio": "SCORPIO",
      "sagittarius": "SAGITTARIUS",
      "capricorn": "CAPRICORN",
      "aquarius": "AQUARIUS",
      "pisces": "PISCES"
    },
    "months": {
      "1": "January",
      "2": "February",
      "3": "March",
      "4": "April",
      "5": "May",
      "6": "June",
      "7": "July",
      "8": "August",
      "9": "September",
      "10": "October",
      "11": "November",
      "12": "December"
    },
    "parapegma": {
      "pleiades": "Pleiades",
      "arcturus": "Arcturus",
      "sirius": "Sirius",
      "hyades": "Hyades",
      "orion": "Orion",
      "lyra": "Lyra",
      "aquila": "Aquila",
      "canis": "Canis",
      "cassiopeia": "Cassiopeia",
      "perseus": "Perseus",
      "andromeda": "Andromeda",
      "pegasus": "Pegasus"
    }
  },
  "greek": {
    "front_face": {
      "title": "ΠΡΟΣΟΨΙΣ",
      "mean_time": "ΜΕΣΗ ΩΡΑ",
      "mean_time_subtitle": "",
      "apparent_time": "ΦΑΙΝΟΜΕΝΗ ΩΡΑ",
      "apparent_time_subtitle": "(Apparent Time)",
      "sundial_ahead": "ΗΛΙΑΚΟ ΡΟΛΟΙ ΜΠΡΟΣΤΑ",
      "sundial_behind": "ΗΛΙΑΚΟ ΡΟΛΟΙ ΠΙΣΩ",
      "local_time": "ΤΟΠΙΚΗ ΩΡΑ"
    },
    "back_upper_face": {
      "title": "ΚΥΚΛΟΣ ΤΟΥ ΜΕΤΩΝΟΣ",
      "year_month": "Έτος {year}/19 — Μήνας {month}/235",
      "cycle_ends": "Ο κύκλος τελειώνει σε {years}έ {days}η (19.0 ηλιακά έτη)",
      "progress": "Πρόοδος: {percent}%",
      "callippic": "Καλλιππικός",
      "years_76": "76 έτη"
    },
    "back_lower_face": {
      "title": "ΚΥΚΛΟΣ ΣΑΡΟΣ",
      "saros_month": "Κύκλος Σάρος {cycle} — Μήνας {month}/223",
      "cycle_ends": "Ο κύκλος τελειώνει σε {years}έ {days}η (≈ 6586.3 ημέρες σύνολο)",
      "next_eclipse_solar": "Επόμενη Έκλειψη: Ηλιακή ☉ σε {days} ημέρες",
      "next_eclipse_lunar": "Επόμενη Έκλειψη: Σεληνιακή ☽ σε {days} ημέρες",
      "progress": "Πρόοδος: {percent}%",
      "exeligmos": "Εξελιγμός",
      "years_54": "54 έτη"
    },
    "zodiac": {
      "aries": "ΚΡΙΟΣ",
      "taurus": "ΤΑΥΡΟΣ",
      "gemini": "ΔΙΔΥΜΟΙ",
      "cancer": "ΚΑΡΚΙΝΟΣ",
      "leo": "ΛΕΩΝ",
      "virgo": "ΠΑΡΘΕΝΟΣ",
      "libra": "ΖΥΓΟΣ",
      "scorpio": "ΣΚΟΡΠΙΟΣ",
      "sagittarius": "ΤΟΞΟΤΗΣ",
      "capricorn": "ΑΙΓΟΚΕΡΩΣ",
      "aquarius": "ΥΔΡΟΧΟΟΣ",
      "pisces": "ΙΧΘΥΕΣ"
    },
    "months": {
      "1": "ΦΑΩΦΙ",
      "2": "ΑΘΥΡ",
      "3": "ΧΟΙΑΚ",
      "4": "ΤΥΒΙ",
      "5": "ΜΕΧΕΙΡ",
      "6": "ΦΑΜΕΝΩΘ",
      "7": "ΦΑΡΜΟΥΘΙ",
      "8": "ΠΑΧΩΝ",
      "9": "ΠΑΥΝΙ",
      "10": "ΕΠΕΙΦ",
      "11": "ΜΕΣΟΡΗ",
      "12": "ΘΩΥΘ"
    },
    "parapegma": {
      "pleiades": "ΠΛΕΙΑΔΕΣ",
      "arcturus": "ΑΡΚΤΟΥΡΟΣ",
      "sirius": "ΣΕΙΡΙΟΣ",
      "hyades": "ΥΑΔΕΣ",
      "orion": "ΩΡΙΩΝ",
      "lyra": "ΛΥΡΑ",
      "aquila": "ΑΕΤΟΣ",
      "canis": "ΚΥΩΝ",
      "cassiopeia": "ΚΑΣΣΙΟΠΕΙΑ",
      "perseus": "ΠΕΡΣΕΥΣ",
      "andromeda": "ΑΝΔΡΟΜΕΔΑ",
      "pegasus": "ΠΗΓΑΣΟΣ"
    }
  },
  "spanish": {
    "front_face": {
      "title": "CARA FRONTAL",
      "mean_time": "TIEMPO MEDIO",
      "mean_time_subtitle": "(Tiempo del Reloj)",
      "apparent_time": "TIEMPO APARENTE",
      "apparent_time_subtitle": "(Tiempo Solar)",
      "sundial_ahead": "Reloj de Sol ADELANTADO",
      "sundial_behind": "Reloj de Sol ATRASADO",
      "local_time": "Hora Local"
    },
    "back_upper_face": {
      "title": "Ciclo Metónico",
      "year_month": "Año {year}/19 — Mes {month}/235",
      "cycle_ends": "El ciclo termina en {years}a {days}d (19.0 años solares)",
      "progress": "Progreso: {percent}%",
      "callippic": "Calípico",
      "years_76": "76 años"
    },
    "back_lower_face": {
      "title": "Ciclo de Saros",
      "saros_month": "Ciclo de Saros {cycle} — Mes {month}/223",
      "cycle_ends": "El ciclo termina en {years}a {days}d (≈ 6586.3 días en total)",
      "next_eclipse_solar": "Próximo Eclipse: Solar ☉ en {days} días",
      "next_eclipse_lunar": "Próximo Eclipse: Lunar ☽ en {days} días",
      "progress": "Progreso: {percent}%",
      "exeligmos": "Exeligmos",
      "years_54": "54 años"
    },
    "zodiac": {
      "aries": "ARIES",
      "taurus": "TAURO",
      "gemini": "GÉMINIS",
      "cancer": "CÁNCER",
      "leo": "LEO",
      "virgo": "VIRGO",
      "libra": "LIBRA",
      "scorpio": "ESCORPIO",
      "sagittarius": "SAGITARIO",
      "capricorn": "CAPRICORNIO",
      "aquarius": "ACUARIO",
      "pisces": "PISCIS"
    },
    "months": {
      "1": "Enero",
      "2": "Febrero",
      "3": "Marzo",
      "4": "Abril",
      "5": "Mayo",
      "6": "Junio",
      "7": "Julio",
      "8": "Agosto",
      "9": "Septiembre",
      "10": "Octubre",
      "11": "Noviembre",
      "12": "Diciembre"
    },
    "parapegma": {
      "pleiades": "Pléyades",
      "arcturus": "Arturo",
      "sirius": "Sirio",
      "hyades": "Híades",
      "orion": "Orión",
      "lyra": "Lira",
      "aquila": "Águila",
      "canis": "Can Mayor",
      "cassiopeia": "Casiopea",
      "perseus": "Perseo",
      "andromeda": "Andrómeda",
      "pegasus": "Pegaso"
    }
  },
  "french": {
    "front_face": {
      "title": "FACE AVANT",
      "mean_time": "TEMPS MOYEN",
      "mean_time_subtitle": "(Heure de l'Horloge)",
      "apparent_time": "TEMPS APPARENT",
      "apparent_time_subtitle": "(Heure Solaire)",
      "sundial_ahead": "Cadran Solaire EN AVANCE",
      "sundial_behind": "Cadran Solaire EN RETARD",
      "local_time": "Heure Locale"
    },
    "back_upper_face": {
      "title": "Cycle de Méton",
      "year_month": "Année {year}/19 — Mois {month}/235",
      "cycle_ends": "Le cycle se termine dans {years}a {days}j (19.0 années solaires)",
      "progress": "Progrès: {percent}%",
      "callippic": "Callippique",
      "years_76": "76 ans"
    },
    "back_lower_face": {
      "title": "Cycle de Saros",
      "saros_month": "Cycle de Saros {cycle} — Mois {month}/223",
      "cycle_ends": "Le cycle se termine dans {years}a {days}j (≈ 6586.3 jours au total)",
      "next_eclipse_solar": "Prochaine Éclipse: Solaire ☉ dans {days} jours",
      "next_eclipse_lunar": "Prochaine Éclipse: Lunaire ☽ dans {days} jours",
      "progress": "Progrès: {percent}%",
      "exeligmos": "Exeligmos",
      "years_54": "54 ans"
    },
    "zodiac": {
      "aries": "BÉLIER",
      "taurus": "TAUREAU",
      "gemini": "GÉMEAUX",
      "cancer": "CANCER",
      "leo": "LION",
      "virgo": "VIERGE",
      "libra": "BALANCE",
      "scorpio": "SCORPION",
      "sagittarius": "SAGITTAIRE",
      "capricorn": "CAPRICORNE",
      "aquarius": "VERSEAU",
      "pisces": "POISSONS"
    },
    "months": {
      "1": "Janvier",
      "2": "Février",
      "3": "Mars",
      "4": "Avril",
      "5": "Mai",
      "6": "Juin",
      "7": "Juillet",
      "8": "Août",
      "9": "Septembre",
      "10": "Octobre",
      "11": "Novembre",
      "12": "Décembre"
    },
    "parapegma": {
      "pleiades": "Pléiades",
      "arcturus": "Arcturus",
      "sirius": "Sirius",
      "hyades": "Hyades",
      "orion": "Orion",
      "lyra": "Lyre",
      "aquila": "Aigle",
      "canis": "Grand Chien",
      "cassiopeia": "Cassiopée",
      "perseus": "Persée",
      "andromeda": "Andromède",
      "pegasus": "Pégase"
    }
  },
  "russian": {
    "front_face": {
      "title": "ПЕРЕДНЯЯ СТОРОНА",
      "mean_time": "СРЕДНЕЕ ВРЕМЯ",
      "mean_time_subtitle": "(Часовое Время)",
      "apparent_time": "ВИДИМОЕ ВРЕМЯ",
      "apparent_time_subtitle": "(Солнечное Время)",
      "sundial_ahead": "Солнечные Часы СПЕШАТ",
      "sundial_behind": "Солнечные Часы ОТСТАЮТ",
      "local_time": "Местное Время"
    },
    "back_upper_face": {
      "title": "Метонов Цикл",
      "year_month": "Год {year}/19 — Месяц {month}/235",
      "cycle_ends": "Цикл заканчивается через {years}л {days}д (19.0 солнечных лет)",
      "progress": "Прогресс: {percent}%",
      "callippic": "Каллиппов",
      "years_76": "76 лет"
    },
    "back_lower_face": {
      "title": "Цикл Сароса",
      "saros_month": "Цикл Сароса {cycle} — Месяц {month}/223",
      "cycle_ends": "Цикл заканчивается через {years}л {days}д (≈ 6586.3 дней всего)",
      "next_eclipse_solar": "Следующее Затмение: Солнечное ☉ через {days} дней",
      "next_eclipse_lunar": "Следующее Затмение: Лунное ☽ через {days} дней",
      "progress": "Прогресс: {percent}%",
      "exeligmos": "Эксэлигмос",
      "years_54": "54 года"
    },
    "zodiac": {
      "aries": "ОВЕН",
      "taurus": "ТЕЛЕЦ",
      "gemini": "БЛИЗНЕЦЫ",
      "cancer": "РАК",
      "leo": "ЛЕВ",
      "virgo": "ДЕВА",
      "libra": "ВЕСЫ",
      "scorpio": "СКОРПИОН",
      "sagittarius": "СТРЕЛЕЦ",
      "capricorn": "КОЗЕРОГ",
      "aquarius": "ВОДОЛЕЙ",
      "pisces": "РЫБЫ"
    },
    "months": {
      "1": "Январь",
      "2": "Февраль",
      "3": "Март",
      "4": "Апрель",
      "5": "Май",
      "6": "Июнь",
      "7": "Июль",
      "8": "Август",
      "9": "Сентябрь",
      "10": "Октябрь",
      "11": "Ноябрь",
      "12": "Декабрь"
    },
    "parapegma": {
      "pleiades": "Плеяды",
      "arcturus": "Арктур",
      "sirius": "Сириус",
      "hyades": "Гиады",
      "orion": "Орион",
      "lyra": "Лира",
      "aquila": "Орёл",
      "canis": "Большой Пёс",
      "cassiopeia": "Кассиопея",
      "perseus": "Персей",
      "andromeda": "Андромеда",
      "pegasus": "Пегас"
    }
  },
  "arabic": {
    "front_face": {
      "title": "الواجهة الأمامية",
      "mean_time": "الوقت المتوسط",
      "mean_time_subtitle": "(وقت الساعة)",
      "apparent_time": "الوقت الظاهري",
      "apparent_time_subtitle": "(الوقت الشمسي)",
      "sundial_ahead": "المزولة متقدمة",
      "sundial_behind": "المزولة متأخرة",
      "local_time": "الوقت المحلي"
    },
    "back_upper_face": {
      "title": "دورة ميتون",
      "year_month": "السنة {year}/19 — الشهر {month}/235",
      "cycle_ends": "تنتهي الدورة في {years}س {days}ي (19.0 سنة شمسية)",
      "progress": "التقدم: {percent}%",
      "callippic": "كاليبيك",
      "years_76": "76 سنة"
    },
    "back_lower_face": {
      "title": "دورة ساروس",
      "saros_month": "دورة ساروس {cycle} — الشهر {month}/223",
      "cycle_ends": "تنتهي الدورة في {years}س {days}ي (≈ 6586.3 يوم إجمالي)",
      "next_eclipse_solar": "الكسوف التالي: شمسي ☉ في {days} يوم",
      "next_eclipse_lunar": "الكسوف التالي: قمري ☽ في {days} يوم",
      "progress": "التقدم: {percent}%",
      "exeligmos": "إكسيليغموس",
      "years_54": "54 سنة"
    },
    "zodiac": {
      "aries": "الحمل",
      "taurus": "الثور",
      "gemini": "الجوزاء",
      "cancer": "السرطان",
      "leo": "الأسد",
      "virgo": "العذراء",
      "libra": "الميزان",
      "scorpio": "العقرب",
      "sagittarius": "القوس",
      "capricorn": "الجدي",
      "aquarius": "الدلو",
      "pisces": "الحوت"
    },
    "months": {
      "1": "يناير",
      "2": "فبراير",
      "3": "مارس",
      "4": "أبريل",
      "5": "مايو",
      "6": "يونيو",
      "7": "يوليو",
      "8": "أغسطس",
      "9": "سبتمبر",
      "10": "أكتوبر",
      "11": "نوفمبر",
      "12": "ديسمبر"
    },
    "parapegma": {
      "pleiades": "الثريا",
      "arcturus": "السماك الرامح",
      "sirius": "الشعرى اليمانية",
      "hyades": "الهيادس",
      "orion": "الجبار",
      "lyra": "القيثارة",
      "aquila": "العقاب",
      "canis": "الكلب الأكبر",
      "cassiopeia": "ذات الكرسي",
      "perseus": "حامل رأس الغول",
      "andromeda": "المرأة المسلسلة",
      "pegasus": "الفرس الأعظم"
    }
  },
  "chinese": {
    "front_face": {
      "title": "正面",
      "mean_time": "平均时间",
      "mean_time_subtitle": "(钟表时间)",
      "apparent_time": "视时",
      "apparent_time_subtitle": "(日晷时间)",
      "sundial_ahead": "日晷快",
      "sundial_behind": "日晷慢",
      "local_time": "当地时间"
    },
    "back_upper_face": {
      "title": "默冬章",
      "year_month": "第{year}/19年 — 第{month}/235月",
      "cycle_ends": "周期在{years}年{days}天后结束 (19.0太阳年)",
      "progress": "进度: {percent}%",
      "callippic": "卡利波斯",
      "years_76": "76年"
    },
    "back_lower_face": {
      "title": "沙罗周期",
      "saros_month": "沙罗周期{cycle} — 第{month}/223月",
      "cycle_ends": "周期在{years}年{days}天后结束 (≈ 6586.3天总计)",
      "next_eclipse_solar": "下次日食: ☉ {days}天后",
      "next_eclipse_lunar": "下次月食: ☽ {days}天后",
      "progress": "进度: {percent}%",
      "exeligmos": "三沙罗周期",
      "years_54": "54年"
    },
    "zodiac": {
      "aries": "白羊座",
      "taurus": "金牛座",
      "gemini": "双子座",
      "cancer": "巨蟹座",
      "leo": "狮子座",
      "virgo": "处女座",
      "libra": "天秤座",
      "scorpio": "天蝎座",
      "sagittarius": "射手座",
      "capricorn": "摩羯座",
      "aquarius": "水瓶座",
      "pisces": "双鱼座"
    },
    "months": {
      "1": "一月",
      "2": "二月",
      "3": "三月",
      "4": "四月",
      "5": "五月",
      "6": "六月",
      "7": "七月",
      "8": "八月",
      "9": "九月",
      "10": "十月",
      "11": "十一月",
      "12": "十二月"
    },
    "parapegma": {
      "pleiades": "昴宿星团",
      "arcturus": "大角星",
      "sirius": "天狼星",
      "hyades": "毕宿星团",
      "orion": "猎户座",
      "lyra": "天琴座",
      "aquila": "天鹰座",
      "canis": "大犬座",
      "cassiopeia": "仙后座",
      "perseus": "英仙座",
      "andromeda": "仙女座",
      "pegasus": "飞马座"
    }
  },
  "japanese": {
    "front_face": {
      "title": "前面",
      "mean_time": "平均時",
      "mean_time_subtitle": "(時計の時刻)",
      "apparent_time": "視太陽時",
      "apparent_time_subtitle": "(日時計の時刻)",
      "sundial_ahead": "日時計が進んでいます",
      "sundial_behind": "日時計が遅れています",
      "local_time": "現地時刻"
    },
    "back_upper_face": {
      "title": "メトン周期",
      "year_month": "第{year}/19年 — 第{month}/235月",
      "cycle_ends": "周期は{years}年{days}日後に終了 (19.0太陽年)",
      "progress": "進捗: {percent}%",
      "callippic": "カリポス",
      "years_76": "76年"
    },
    "back_lower_face": {
      "title": "サロス周期",
      "saros_month": "サロス周期{cycle} — 第{month}/223月",
      "cycle_ends": "周期は{years}年{days}日後に終了 (≈ 6586.3日合計)",
      "next_eclipse_solar": "次の日食: ☉ {days}日後",
      "next_eclipse_lunar": "次の月食: ☽ {days}日後",
      "progress": "進捗: {percent}%",
      "exeligmos": "エクセリグモス",
      "years_54": "54年"
    },
    "zodiac": {
      "aries": "牡羊座",
      "taurus": "牡牛座",
      "gemini": "双子座",
      "cancer": "蟹座",
      "leo": "獅子座",
      "virgo": "乙女座",
      "libra": "天秤座",
      "scorpio": "蠍座",
      "sagittarius": "射手座",
      "capricorn": "山羊座",
      "aquarius": "水瓶座",
      "pisces": "魚座"
    },
    "months": {
      "1": "1月",
      "2": "2月",
      "3": "3月",
      "4": "4月",
      "5": "5月",
      "6": "6月",
      "7": "7月",
      "8": "8月",
      "9": "9月",
      "10": "10月",
      "11": "11月",
      "12": "12月"
    },
    "parapegma": {
      "pleiades": "プレアデス星団",
      "arcturus": "アークトゥルス",
      "sirius": "シリウス",
      "hyades": "ヒアデス星団",
      "orion": "オリオン座",
      "lyra": "こと座",
      "aquila": "わし座",
      "canis": "おおいぬ座",
      "cassiopeia": "カシオペヤ座",
      "perseus": "ペルセウス座",
      "andromeda": "アンドロメダ座",
      "pegasus": "ペガスス座"
    }
  },
  "klingon": {
    "front_face": {
      "title": "QUN BEJ",
      "mean_time": "POH NUGH",
      "mean_time_subtitle": "(mIv poH)",
      "apparent_time": "POH'E' LEG",
      "apparent_time_subtitle": "(pemjep poH)",
      "sundial_ahead": "pemjep RUSTO'",
      "sundial_behind": "pemjep TAI'",
      "local_time": "NUGH poH"
    },
    "back_upper_face": {
      "title": "METON MACH",
      "year_month": "DIS {year}/19 — jar {month}/235",
      "cycle_ends": "MACH mach {years}y {days}d (19.0 pemjep DIS)",
      "progress": "TAGH: {percent}%",
      "callippic": "KALLIPIK",
      "years_76": "76 DIS"
    },
    "back_lower_face": {
      "title": "SAROS MACH",
      "saros_month": "SAROS MACH {cycle} — jar {month}/223",
      "cycle_ends": "MACH mach {years}y {days}d (≈ 6586.3 jaj)",
      "next_eclipse_solar": "VITH: pemjep ☉ {days} jaj",
      "next_eclipse_lunar": "VITH: maS ☽ {days} jaj",
      "progress": "TAGH: {percent}%",
      "exeligmos": "EKSELIGMOS",
      "years_54": "54 DIS"
    },
    "zodiac": {
      "aries": "QI'",
      "taurus": "TARGH",
      "gemini": "CHA' LOM",
      "cancer": "GHEW",
      "leo": "QI'EMPEQ",
      "virgo": "BE' QUVHAH",
      "libra": "NAGH",
      "scorpio": "GHEW NAGH",
      "sagittarius": "BEQ",
      "capricorn": "RA'GHOM",
      "aquarius": "BIQ",
      "pisces": "GHOTHMEY"
    },
    "months": {
      "1": "wa'DIch jar",
      "2": "cha'DIch jar",
      "3": "wejDIch jar",
      "4": "loSDIch jar",
      "5": "vaghDIch jar",
      "6": "jAvDIch jar",
      "7": "SochDIch jar",
      "8": "chorghDIch jar",
      "9": "HutDIch jar",
      "10": "wa'maH jar",
      "11": "wa'maHwa' jar",
      "12": "wa'maHcha' jar"
    },
    "parapegma": {
      "pleiades": "HOVMEY MACH",
      "arcturus": "HOV TIQH",
      "sirius": "HOV WOVQU'",
      "hyades": "HOVMEY V",
      "orion": "SUQQA'",
      "lyra": "CHORD",
      "aquila": "TOQDUQ",
      "canis": "TARGH QI'",
      "cassiopeia": "QASIOPEIA",
      "perseus": "PER'SU'",
      "andromeda": "'ANDROMEDA",
      "pegasus": "SARGH YUVTLHE'"
    }
  }
}
